Workbook

Sheet Title
AC1: ИНН | DP1: Приложение № 4 к Приказу ФНС РФ от 24.11.2011 № ММВ-7-11/895
AC4: КПП | BL4: Стр. | BR4: 0 | BU4: 0 | BX4: 1
DP7: Форма по КНД 1152028
A8: Налоговый расчет по авансовому платежу по налогу на имущество организаций
V10: Номер корректировки | X10: 0 | AA10: - | AD10: - | BT10: Отчетный период (код) | DC10: Отчетный год
D12: Представляется в налоговый орган (код) | DF12: по месту нахождения (учета) (код)
A21: (налогоплательщик)
CE23: Код вида экономической деятельности по классификатору ОКВЭД | CM23: . | CV23: .
A24: Форма реорганизации (код) | AE24: ИНН/КПП реорганизованной организации
CN25: /
AI27: Номер контактного телефона
A29: На | O29: страницах | CW29: с приложением подтверждающих документов или их копий на | DI29: листах
A31: Достоверность и полноту сведений, указанных | BJ31: Заполняется работником налогового органа
A32: в настоящем расчете, подтверждаю:
BJ33: Сведения о представлении расчета
Q34: 1 - налогоплательщик, 2 - представитель налогоплательщика
BK35: Данный расчет представлен (код)
BN38: на | CP38: страницах
BJ41: с приложением подтверждающих документов или их копий на
DC44: листах
A46: (фамилия, имя, отчество полностью)
BK48: Дата представления расчета | CR48: . | DA48: .
BK52: Зарегистрирован за №
BN60: (Фамилия, И.О.) | CR60: (Подпись)
A67: (наименование организации - представителя налогоплательщика)
A68: Подпись
Y69: Дата | AK69: . | AT69: .
L71: М.П.
A72: Наименование документа,
A73: подтверждающего полномочия представителя

Sheet 00001
AC1: ИНН | AK1: =IF(ISBLANK(Title!AK1),"",Title!AK1) | AN1: =IF(ISBLANK(Title!AN1),"",Title!AN1) | AQ1: =IF(ISBLANK(Title!AQ1),"",Title!AQ1) | AT1: =IF(ISBLANK(Title!AT1),"",Title!AT1) | AW1: =IF(ISBLANK(Title!AW1),"",Title!AW1) | AZ1: =IF(ISBLANK(Title!AZ1),"",Title!AZ1) | BC1: =IF(ISBLANK(Title!BC1),"",Title!BC1) | BF1: =IF(ISBLANK(Title!BF1),"",Title!BF1) | BI1: =IF(ISBLANK(Title!BI1),"",Title!BI1) | BL1: =IF(ISBLANK(Title!BL1),"",Title!BL1) | BO1: =IF(ISBLANK(Title!BO1),"",Title!BO1) | BR1: =IF(ISBLANK(Title!BR1),"",Title!BR1)
AC4: КПП | AK4: =IF(ISBLANK(Title!AK4),"",Title!AK4) | AN4: =IF(ISBLANK(Title!AN4),"",Title!AN4) | AQ4: =IF(ISBLANK(Title!AQ4),"",Title!AQ4) | AT4: =IF(ISBLANK(Title!AT4),"",Title!AT4) | AW4: =IF(ISBLANK(Title!AW4),"",Title!AW4) | AZ4: =IF(ISBLANK(Title!AZ4),"",Title!AZ4) | BC4: =IF(ISBLANK(Title!BC4),"",Title!BC4) | BF4: =IF(ISBLANK(Title!BF4),"",Title!BF4) | BI4: =IF(ISBLANK(Title!BI4),"",Title!BI4) | BL4: Стр.
A7: Раздел 1. Сумма авансового платежа по налогу, подлежащая уплате в бюджет, по данным налогоплательщика
A9: Показатели | AX9: Код строки | BI9: Значения показателей
A10: 1 | AX10: 2 | BI10: 3
A12: Код ОКАТО | AX12: 010
A14: Код бюджетной классификации | AX14: 020
A15: Сумма авансового платежа по налогу, подлежащая уплате в бюджет (руб.)
AX16: 030
A19: Код ОКАТО | AX19: 010
A21: Код бюджетной классификации | AX21: 020
A22: Сумма авансового платежа по налогу, подлежащая уплате в бюджет (руб.)
AX23: 030
A26: Код ОКАТО | AX26: 010
A28: Код бюджетной классификации | AX28: 020
A29: Сумма авансового платежа по налогу, подлежащая уплате в бюджет (руб.)
AX30: 030
A33: Код ОКАТО | AX33: 010
A35: Код бюджетной классификации | AX35: 020
A36: Сумма авансового платежа по налогу, подлежащая уплате в бюджет (руб.)
AX37: 030
A40: Код ОКАТО | AX40: 010
A42: Код бюджетной классификации | AX42: 020
A43: Сумма авансового платежа по налогу, подлежащая уплате в бюджет (руб.)
AX44: 030
A47: Код ОКАТО | AX47: 010
A49: Код бюджетной классификации | AX49: 020
A50: Сумма авансового платежа по налогу, подлежащая уплате в бюджет (руб.)
AX51: 030
A54: Код ОКАТО | AX54: 010
A56: Код бюджетной классификации | AX56: 020
A57: Сумма авансового платежа по налогу, подлежащая уплате в бюджет (руб.)
AX58: 030
A67: Достоверность и полноту сведений, указанных на данной странице, подтверждаю:
AV69: (подпись) | CG69: (дата)

Sheet 00002
AC1: ИНН | AK1: =IF(ISBLANK(Title!AK1),"",Title!AK1) | AN1: =IF(ISBLANK(Title!AN1),"",Title!AN1) | AQ1: =IF(ISBLANK(Title!AQ1),"",Title!AQ1) | AT1: =IF(ISBLANK(Title!AT1),"",Title!AT1) | AW1: =IF(ISBLANK(Title!AW1),"",Title!AW1) | AZ1: =IF(ISBLANK(Title!AZ1),"",Title!AZ1) | BC1: =IF(ISBLANK(Title!BC1),"",Title!BC1) | BF1: =IF(ISBLANK(Title!BF1),"",Title!BF1) | BI1: =IF(ISBLANK(Title!BI1),"",Title!BI1) | BL1: =IF(ISBLANK(Title!BL1),"",Title!BL1) | BO1: =IF(ISBLANK(Title!BO1),"",Title!BO1) | BR1: =IF(ISBLANK(Title!BR1),"",Title!BR1)
AC4: КПП | AK4: =IF(ISBLANK(Title!AK4),"",Title!AK4) | AN4: =IF(ISBLANK(Title!AN4),"",Title!AN4) | AQ4: =IF(ISBLANK(Title!AQ4),"",Title!AQ4) | AT4: =IF(ISBLANK(Title!AT4),"",Title!AT4) | AW4: =IF(ISBLANK(Title!AW4),"",Title!AW4) | AZ4: =IF(ISBLANK(Title!AZ4),"",Title!AZ4) | BC4: =IF(ISBLANK(Title!BC4),"",Title!BC4) | BF4: =IF(ISBLANK(Title!BF4),"",Title!BF4) | BI4: =IF(ISBLANK(Title!BI4),"",Title!BI4) | BL4: Стр.
A7: Раздел 2. Исчисление суммы авансового платежа по налогу в отношении подлежащего налогообложению
A8: имущества российских организаций и иностранных организаций, осуществляющих деятельность в Российской
A9: Федерации через постоянные представительства
BO11: Код ОКАТО (код строки 010)
W12: Код вида имущества
A15: Данные для расчета средней стоимости имущества за отчетный период
A17: По состоянию на: | P17: Код строки | X17: Остаточная стоимость основных средств
X18: Всего | BU18: в т.ч. стоимость льготируемого имущества
A19: 1 | P19: 2 | X19: 3 | BU19: 4
A21: 01.01 | P21: 020
A23: 01.02 | P23: 030
A25: 01.03 | P25: 040
A27: 01.04 | P27: 050
A29: 01.05 | P29: 060
A31: 01.06 | P31: 070
A33: 01.07 | P33: 080
A35: 01.08 | P35: 090
A37: 01.09 | P37: 100
A39: 01.10 | P39: 110
A41: Расчет суммы авансового платежа по налогу
F43: Показатели | AV43: Код строки | BJ43: Значение показателей
A44: 1 | AZ44: 2 | BF44: 3
A46: Средняя стоимость имущества за отчетный период
AZ47: 120
A49: Код налоговой льготы | AZ49: 130 | CA49: /
A51: Средняя стоимость необлагаемого налогом имущества за отчетный период
AZ52: 140
A54: Доля балансовой стоимости объекта недвижимого имущества на территории соответствующего субъекта Российской Федерации
AZ55: 150 | CJ55: /
A57: Код налоговой льготы (установленной в виде понижения налоговой ставки)
AZ58: 160 | CA58: /
A60: Налоговая ставка (%) | AZ60: 170 | BI60: .
A62: Сумма авансового платежа | AZ62: 180
A64: Код налоговой льготы (в виде уменьшения суммы налога, подлежащей уплате в бюджет)
AZ65: 190 | CA65: /
A67: Сумма льготы по авансовому платежу, уменьшающей сумму авансового платежа по налогу, подлежащую уплате в бюджет
AZ68: 200

Sheet 00003
AC1: ИНН | AK1: =IF(ISBLANK(Title!AK1),"",Title!AK1) | AN1: =IF(ISBLANK(Title!AN1),"",Title!AN1) | AQ1: =IF(ISBLANK(Title!AQ1),"",Title!AQ1) | AT1: =IF(ISBLANK(Title!AT1),"",Title!AT1) | AW1: =IF(ISBLANK(Title!AW1),"",Title!AW1) | AZ1: =IF(ISBLANK(Title!AZ1),"",Title!AZ1) | BC1: =IF(ISBLANK(Title!BC1),"",Title!BC1) | BF1: =IF(ISBLANK(Title!BF1),"",Title!BF1) | BI1: =IF(ISBLANK(Title!BI1),"",Title!BI1) | BL1: =IF(ISBLANK(Title!BL1),"",Title!BL1) | BO1: =IF(ISBLANK(Title!BO1),"",Title!BO1) | BR1: =IF(ISBLANK(Title!BR1),"",Title!BR1)
AC4: КПП | AK4: =IF(ISBLANK(Title!AK4),"",Title!AK4) | AN4: =IF(ISBLANK(Title!AN4),"",Title!AN4) | AQ4: =IF(ISBLANK(Title!AQ4),"",Title!AQ4) | AT4: =IF(ISBLANK(Title!AT4),"",Title!AT4) | AW4: =IF(ISBLANK(Title!AW4),"",Title!AW4) | AZ4: =IF(ISBLANK(Title!AZ4),"",Title!AZ4) | BC4: =IF(ISBLANK(Title!BC4),"",Title!BC4) | BF4: =IF(ISBLANK(Title!BF4),"",Title!BF4) | BI4: =IF(ISBLANK(Title!BI4),"",Title!BI4) | BL4: Стр.
A7: Раздел 3. Исчисление суммы авансового платежа по налогу за отчетный период по объекту недвижимого
A8: имущества иностранной организации, не относящемуся к ее деятельности в Российской Федерации через
A9: постоянное представительство
AA11: Код ОКАТО (код строки 010)
A15: Показатели | AX15: Код строки | BF15: Значение показателей
A16: 1 | AX16: 2 | BF16: 3
A18: Инвентаризационная стоимость на 1 января налогового периода
AX19: 020
A20: в том числе необлагаемая налогом инвентаризационная стоимость
AX21: 030
A23: Код налоговой льготы | AX23: 040 | CA23: /
A24: Доля инвентаризационной стоимости объекта недвижимого имущества на территории субъекта Российской Федерации
AX25: 050 | CJ25: /
A27: Код налоговой льготы (установленной в виде понижения налоговой ставки)
AX28: 060 | CA28: /
A30: Налоговая ставка (%) | AX30: 070 | BI30: .
A32: Коэффициент К | AX32: 080 | BI32: /
A34: Сумма авансового платежа по налогу | AX34: 090
A35: Код налоговой льготы (в виде уменьшения суммы налога, подлежащей уплате в бюджет)
AX36: 100 | CA36: /
A37: Сумма льготы по авансовому платежу, уменьшающей сумму авансового платежа по налогу, подлежащую уплате в бюджет
AX38: 110

Sheet Info
