Workbook

Sheet Title
AB1: ИНН | DP1: Приложение № 3 к Приказу Минфина РФ от 20.02.2008 № 27н
AB4: КПП | BK4: Стр. | BQ4: 0 | BT4: 0 | BW4: 0 | BZ4: 0 | CC4: 0 | CF4: 1
CI6: Форма по КНД 1152028
A8: Налоговый расчет по авансовому платежу по налогу на имущество организаций
A10: Номер корректировки | BS10: Отчетный период (код) | DC10: Отчетный год
D12: Представляется в налоговый орган (код) | BT12: по месту нахождения (учета) (код)
A21: (налогоплательщик)
CE23: Код вида экономической деятельности по классификатору ОКВЭД | CM23: . | CV23: .
AJ25: Номер контактного телефона
A27: На | W27: страницах | CO27: с приложением подтверждающих документов или их копий на | DI27: листах
A30: Достоверность и полноту сведений, указанных | BK30: Заполняется работником налогового органа
A31: в настоящем расчете, подтверждаю:
R33: 1 - налогоплательщик, 2 - представитель налогоплательщика
BK34: Сведения о представлении расчета
DE36: Данный расчет представлен (код)
BM40: на | CW40: страницах
B41: (фамилия, имя, отчество полностью)
BL42: с приложением подтверждающих документов и (или) их копий на
DI44: листах
B47: (наименование организации - представителя налогоплательщика) | BL47: Дата представления расчета
CQ48: . | CZ48: .
B50: Подпись | Y50: Дата | AL50: . | AU50: .
L51: М.П.
A53: Наименование документа, | BL53: Зарегистрирован за №
A54: подтверждающего полномочия представителя
BP60: (Фамилия, И.О.) | CU60: (Подпись)

Sheet 00001
AB1: ИНН | AJ1: =Title!AJ1 -> 0 | AM1: =Title!AM1 -> 0 | AP1: =Title!AP1 -> 0 | AS1: =Title!AS1 -> 0 | AV1: =Title!AV1 -> 0 | AY1: =Title!AY1 -> 0 | BB1: =Title!BB1 -> 0 | BE1: =Title!BE1 -> 0 | BH1: =Title!BH1 -> 0 | BK1: =Title!BK1 -> 0 | BN1: =Title!BN1 -> 0 | BQ1: =Title!BQ1 -> 0
AB4: КПП | AJ4: =Title!AJ4 -> 0 | AM4: =Title!AM4 -> 0 | AP4: =Title!AP4 -> 0 | AS4: =Title!AS4 -> 0 | AV4: =Title!AV4 -> 0 | AY4: =Title!AY4 -> 0 | BB4: =Title!BB4 -> 0 | BE4: =Title!BE4 -> 0 | BH4: =Title!BH4 -> 0 | BK4: Стр. | BQ4: 0 | BT4: 0 | BW4: 0 | BZ4: 0 | CC4: 0 | CF4: 2
A6: Раздел 1. Сумма авансового платежа по налогу, подлежащая уплате в бюджет по данным налогоплательщика
A8: Показатели | AX8: Код строки | BI8: Значения показателей
A11: Код по ОКАТО | AX11: 010
A13: Код бюджетной классификации | AX13: 020
A14: Сумма авансового платежа по налогу, подлежащая уплате в бюджет (руб.)
AX15: 030
A18: Код по ОКАТО | AX18: 010
A20: Код бюджетной классификации | AX20: 020
A21: Сумма авансового платежа по налогу, подлежащая уплате в бюджет (руб.)
AX22: 030
A25: Код по ОКАТО | AX25: 010
A27: Код бюджетной классификации | AX27: 020
A28: Сумма авансового платежа по налогу, подлежащая уплате в бюджет (руб.)
AX29: 030
A32: Код по ОКАТО | AX32: 010
A34: Код бюджетной классификации | AX34: 020
A35: Сумма авансового платежа по налогу, подлежащая уплате в бюджет (руб.)
AX36: 030
A39: Код по ОКАТО | AX39: 010
A41: Код бюджетной классификации | AX41: 020
A42: Сумма авансового платежа по налогу, подлежащая уплате в бюджет (руб.)
AX43: 030
A46: Код по ОКАТО | AX46: 010
A48: Код бюджетной классификации | AX48: 020
A49: Сумма авансового платежа по налогу, подлежащая уплате в бюджет (руб.)
AX50: 030
A53: Код по ОКАТО | AX53: 010
A55: Код бюджетной классификации | AX55: 020
A56: Сумма авансового платежа по налогу, подлежащая уплате в бюджет (руб.)
AX57: 030
A72: Достоверность и полноту сведений, указанных на данной странице, подтверждаю:
AU74: (подпись) | CM74: (дата)

Sheet 00002
AB1: ИНН | AJ1: =Title!AJ1 -> 0 | AM1: =Title!AM1 -> 0 | AP1: =Title!AP1 -> 0 | AS1: =Title!AS1 -> 0 | AV1: =Title!AV1 -> 0 | AY1: =Title!AY1 -> 0 | BB1: =Title!BB1 -> 0 | BE1: =Title!BE1 -> 0 | BH1: =Title!BH1 -> 0 | BK1: =Title!BK1 -> 0 | BN1: =Title!BN1 -> 0 | BQ1: =Title!BQ1 -> 0
AB4: КПП | AJ4: =Title!AJ4 -> 0 | AM4: =Title!AM4 -> 0 | AP4: =Title!AP4 -> 0 | AS4: =Title!AS4 -> 0 | AV4: =Title!AV4 -> 0 | AY4: =Title!AY4 -> 0 | BB4: =Title!BB4 -> 0 | BE4: =Title!BE4 -> 0 | BH4: =Title!BH4 -> 0 | BK4: Стр. | BQ4: 0 | BT4: 0 | BW4: 0 | BZ4: 0 | CC4: 0 | CF4: 3
A6: Раздел 2. Исчисление суммы авансового платежа по налогу в отношении подлежащего налогообложению
A7: имущества российских организаций и иностранных организаций, осуществляющих деятельность
A8: в Российской Федерации через постоянные представительства
BN10: Код по ОКАТО (код строки 010)
W11: Код вида имущества
A14: Данные для расчета средней стоимости имущества за отчетный период
A15: По состоянию на: | M15: Код строки | U15: Остаточная стоимость основных средств
U17: Всего | BT17: в т.ч. стоимость льготируемого имущества
A18: 1 | M18: 2 | U18: 3 | BT18: 4
A19: 01.01 | M19: 020
A21: 01.02 | M21: 030
A23: 01.03 | M23: 040
A25: 01.04 | M25: 050
A27: 01.05 | M27: 060
A29: 01.06 | M29: 070
A31: 01.07 | M31: 080
A33: 01.08 | M33: 090
A35: 01.09 | M35: 100
A37: 01.10 | M37: 110
A39: Расчет суммы авансового платежа по налогу
A40: Показатели | AX40: Код строки | BF40: Значение показателей
A41: 1 | AX41: 2 | BF41: 3
A43: Средняя стоимость имущества за отчетный период | AX43: 120
A45: Код налоговой льготы | AX45: 130
A47: Средняя стоимость не облагаемого налогом имущества за отчетный период
AX48: 140
A50: Доля балансовой стоимости объекта недвижимого имущества на территории соответствующего субъекта Российской Федерации
AX51: 150 | CJ51: /
A53: Код налоговой льготы (установленной в виде понижения налоговой ставки)
AX54: 160
A56: Налоговая ставка (%) | AX56: 170 | BI56: .
A58: Сумма авансового платежа | AX58: 180
A59: Код налоговой льготы (в виде уменьшения суммы налога, подлежащей уплате в бюджет)
AX60: 190
A62: Сумма льготы по авансовому платежу, уменьшающей сумму авансового платежа по налогу, подлежащую уплате в бюджет
AX63: 200

Sheet 00003
AB1: ИНН | AJ1: =Title!AJ1 -> 0 | AM1: =Title!AM1 -> 0 | AP1: =Title!AP1 -> 0 | AS1: =Title!AS1 -> 0 | AV1: =Title!AV1 -> 0 | AY1: =Title!AY1 -> 0 | BB1: =Title!BB1 -> 0 | BE1: =Title!BE1 -> 0 | BH1: =Title!BH1 -> 0 | BK1: =Title!BK1 -> 0 | BN1: =Title!BN1 -> 0 | BQ1: =Title!BQ1 -> 0
AB4: КПП | AJ4: =Title!AJ4 -> 0 | AM4: =Title!AM4 -> 0 | AP4: =Title!AP4 -> 0 | AS4: =Title!AS4 -> 0 | AV4: =Title!AV4 -> 0 | AY4: =Title!AY4 -> 0 | BB4: =Title!BB4 -> 0 | BE4: =Title!BE4 -> 0 | BH4: =Title!BH4 -> 0 | BK4: Стр. | BQ4: 0 | BT4: 0 | BW4: 0 | BZ4: 0 | CC4: 0 | CF4: 4
A6: Раздел 3. Исчисление суммы авансового платежа по налогу за отчетный период по объекту недвижимого
A7: имущества иностранной организации, не относящемуся к ее деятельности в Российской Федерации
A8: через постоянное представительство
AC10: Код по ОКАТО (код строки 010)
A13: Показатели | AX13: Код строки | BF13: Значение показателей
A14: 1 | AX14: 2 | BF14: 3
A15: Инвентаризационная стоимость на 1 января налогового периода
AX16: 020
A18: в том числе не облагаемая налогом инвентаризационная стоимость
AX19: 030
A21: Код налоговой льготы | AX21: 040
A22: Доля инвентаризационной стоимости объекта недвижимого имущества на территории субъекта Российской Федерации
AX23: 050 | CJ23: /
A25: Код налоговой льготы (установленной в виде понижения налоговой ставки)
AX26: 060
A28: Налоговая ставка (%) | AX28: 070 | BI28: .
A30: Коэффициент К | AX30: 080 | BL30: /
A32: Сумма авансового платежа по налогу | AX32: 090
A34: Код налоговой льготы (в виде уменьшения суммы налога, подлежащей уплате в бюджет)
AX35: 100
A37: Сумма льготы по авансовому платежу, уменьшающей сумму авансового платежа по налогу, подлежащую уплате в бюджет
AX38: 110
